atoti_legacy_app/LICENSE
atoti_legacy_app/__init__.py
atoti_legacy_app/_plugin.py
atoti_legacy_app/data/atoti-legacy-app.jar
tests_legacy_app/__init__.py
tests_legacy_app/test_legacy.py
atoti_legacy_app-0.6.2.dist-info/LICENSE
atoti_legacy_app-0.6.2.dist-info/METADATA
atoti_legacy_app-0.6.2.dist-info/WHEEL
atoti_legacy_app-0.6.2.dist-info/entry_points.txt
atoti_legacy_app-0.6.2.dist-info/top_level.txt
atoti_legacy_app-0.6.2.dist-info/RECORD
