Metadata-Version: 2.1
Name: atoti-legacy-app
Version: 0.6.2
Summary: Plugin to serve the legacy app based on ActiveUI 4 at f"{session_url}/legacy/".
Home-page: https://www.atoti.io
Author: atoti
Author-email: dev@atoti.io
License: UNKNOWN
Project-URL: Documentation, https://docs.atoti.io/0.6.2/lib/atoti-legacy-app/atoti_legacy_app.html
Project-URL: Bug Tracker, https://github.com/atoti/atoti/issues
Keywords: atoti,activeui4,legacy,ui
Platform: UNKNOWN
Classifier: Development Status :: 4 - Beta
Classifier: License :: Free To Use But Restricted
Classifier: Operating System :: OS Independent
Classifier: Programming Language :: Java
Classifier: Programming Language :: Python :: 3
Classifier: Typing :: Typed
Requires-Python: >=3.7
License-File: atoti_legacy_app/LICENSE
Requires-Dist: atoti (==0.6.2)
